XStatic_lodash-4.16.4.2-nspkg.pth
XStatic_lodash-4.16.4.2.dist-info/DESCRIPTION.rst
XStatic_lodash-4.16.4.2.dist-info/METADATA
XStatic_lodash-4.16.4.2.dist-info/RECORD
XStatic_lodash-4.16.4.2.dist-info/WHEEL
XStatic_lodash-4.16.4.2.dist-info/metadata.json
XStatic_lodash-4.16.4.2.dist-info/namespace_packages.txt
XStatic_lodash-4.16.4.2.dist-info/top_level.txt
xstatic/pkg/lodash/__init__.py
xstatic/pkg/lodash/data/lodash.core.js
xstatic/pkg/lodash/data/lodash.core.min.js
xstatic/pkg/lodash/data/lodash.fp.js
xstatic/pkg/lodash/data/lodash.fp.min.js
xstatic/pkg/lodash/data/lodash.js
xstatic/pkg/lodash/data/lodash.min.js
xstatic/pkg/lodash/data/mapping.fp.js
