Metadata-Version: 2.0
Name: XStatic-lodash
Version: 4.16.4.2
Summary: lodash 4.16.4 (XStatic packaging standard)
Home-page: https://github.com/lodash/lodash
Maintainer: Michal Arbet
Maintainer-email: michal.arbet@ultimum.io
License: (same as lodash)
Keywords: lodash xstatic
Platform: any
